gio_importer-1.2.6.dist-info/licenses/LICENSE
importers/README.md
importers/__init__.py
importers/clear_user.py
importers/conf.cfg
importers/data_importer.py
importers/format_importer.py
importers/log_conf.yaml
importers/meta_importer.py
importers/saas_export.py
importers/setup.py
importers/trigger_job.py
importers/zk.py
importers/clear_data/__init__.py
importers/clear_data/clear_data.py
importers/common/__init__.py
importers/common/common_util.py
importers/common/config_util.py
importers/common/http_util.py
importers/common/log_util.py
importers/data_import/__init__.py
importers/data_import/data_ads.py
importers/data_import/data_events.py
importers/data_import/data_format_util.py
importers/data_import/data_item_variable.py
importers/data_import/data_model.py
importers/data_import/data_user_variable.py
importers/db_import/__init__.py
importers/db_import/database_import.py
importers/db_import/hive_import.py
importers/db_import/mysql_import.py
importers/example/__init__.py
importers/meta/__init__.py
importers/meta/check_util.py
importers/meta/data_center.py
importers/meta/meta_create.py
importers/saas_export/__init__.py
importers/saas_export/saas_meta.py
gio_importer-1.2.6.dist-info/METADATA
gio_importer-1.2.6.dist-info/WHEEL
gio_importer-1.2.6.dist-info/entry_points.txt
gio_importer-1.2.6.dist-info/top_level.txt
gio_importer-1.2.6.dist-info/RECORD
